sogou_translate.py
sogou_translate-1.0.1.dist-info/DESCRIPTION.rst
sogou_translate-1.0.1.dist-info/METADATA
sogou_translate-1.0.1.dist-info/RECORD
sogou_translate-1.0.1.dist-info/WHEEL
sogou_translate-1.0.1.dist-info/metadata.json
sogou_translate-1.0.1.dist-info/top_level.txt
