Metadata-Version: 2.0
Name: sogou-translate
Version: 1.0.1
Summary: The Python wrapper for Sogou Translate API
Home-page: https://github.com/imWildCat/sogou-translate
Author: Daohan Chong
Author-email: wildcat.name@gmail.com
License: UNKNOWN
Download-URL: https://github.com/imWildCat/sogou-translate/archive/1.0.0.tar.gz
Keywords: translate,api,sougou
Platform: UNKNOWN
Classifier: Programming Language :: Python
Classifier: Programming Language :: Python :: 3.6
Classifier: Programming Language :: Python :: Implementation :: CPython
Classifier: Programming Language :: Python :: Implementation :: PyPy
Requires-Python: >=3.6.0
Requires-Dist: requests
